Workbook

Sheet Dashboard
A2: Total Revenue | C2: Total Profit | E2: Overall Margin % | G2: Latest YoY Revenue Growth %
A3: =Dashboard_Data!B2 -> 2297200.9 | C3: =Overall_Table[[#This Row],[Value]] -> 923588.06 | E3: =Dashboard_Data!B4 -> 0.40204933 | G3: =Dashboard_Data!B5 -> 0.20355962

Sheet Dashboard_Data
A1: Metric | B1: Value
A2: Total Revenue | B2: =Table4[[#This Row],[Value]] -> 2297200.9
A3: Total Profit | B3: =KPI_Calculations!B4 -> 923588.06
A4: Overall Margin % | B4: =KPI_Calculations!B5 -> 0.40204933
A5: Latest YoY Revenue Growth % | B5: =Yearly_Analysis!C7 -> 0.20355962
A8: Year | B8: Revenue
A9: 2014 | B9: =GETPIVOTDATA("Sales",Yearly_Analysis!$A$3,"Year",2014) -> 484247.5
A10: 2015 | B10: =GETPIVOTDATA("Sales",Yearly_Analysis!$A$3,"Year",2015) -> 470532.51
A11: 2016 | B11: =GETPIVOTDATA("Sales",Yearly_Analysis!$A$3,"Year",2016) -> 609205.6
A12: 2017 | B12: =GETPIVOTDATA("Sales",Yearly_Analysis!$A$3,"Year",2017) -> 733215.26
A15: Region | B15: Revenue | C15: Margin %
A16: West | B16: =GETPIVOTDATA("Total Revenue",Region_Analysis!$B$3,"Region","West") -> 725457.82 | C16: =Region_Analysis!E7 -> 0.39995721
A17: East | B17: =GETPIVOTDATA("Total Revenue",Region_Analysis!$B$3,"Region","East") -> 678781.24 | C17: =Region_Analysis!E5 -> 0.40417533
A18: Central | B18: =GETPIVOTDATA("Total Revenue",Region_Analysis!$B$3,"Region","Central") -> 501239.89 | C18: =Region_Analysis!E4 -> 0.40066028
A19: South | B19: =GETPIVOTDATA("Total Revenue",Region_Analysis!$B$3,"Region","South") -> 391721.91 | C19: =Region_Analysis!E6 -> 0.40401729
A22: Category | B22: Revenue | C22: Margin %
A23: Furniture | B23: =GETPIVOTDATA("Total Revenue",Category_Analysis!$A$3,"Category","Furniture") -> 741999.8 | C23: =Category_Analysis!D4 -> 0.35
A24: Office Supplies | B24: =GETPIVOTDATA("Total Revenue",Category_Analysis!$A$3,"Category","Office Supplies") -> 719047.03 | C24: =Category_Analysis!D5 -> 0.4
A25: Technology | B25: =GETPIVOTDATA("Total Revenue",Category_Analysis!$A$3,"Category","Technology") -> 836154.03 | C25: =Category_Analysis!D6 -> 0.45

Sheet KPI_Calculations
A1: KPI | B1: Value | C1: Why it matters
A2: Total Revenue | B2: =SUM(Sales_Data[Sales]) -> 2297200.9 | C2: Shows business size
A3: Total Cost | B3: =SUM(Sales_Data[Cost]) -> 1373612.8 | C3: Shows spending
A4: Total Gross Profit | B4: =SUM(Sales_Data[Gross_Profit_Recalc]) -> 923588.06 | C4: Shows profit after cost
A5: Overall Margin % | B5: =B4/B2 -> 0.40204933 | C5: Shows efficiency

Sheet Assumptions_Model
A1: Category | B1: Assumed Cost % of Sales
A2: Furniture | B2: 0.65
A3: Technology | B3: 0.55
A4: Office Supplies | B4: 0.6

Sheet Yearly_Analysis
A3: Year | B3: Total Revenue | C3: Revenue Growth %
A4: 2014 | B4: 484247.5
A5: 2015 | B5: 470532.51 | C5: =(GETPIVOTDATA("Sales",$A$3,"Year",2015)-GETPIVOTDATA("Sales",$A$3,"Year",2014))/GETPIVOTDATA("Sales",$A$3,"Year",2014) -> -0.028322271
A6: 2016 | B6: 609205.6 | C6: =(GETPIVOTDATA("Sales",$A$3,"Year",2016)-GETPIVOTDATA("Sales",$A$3,"Year",2015))/GETPIVOTDATA("Sales",$A$3,"Year",2015) -> 0.29471521
A7: 2017 | B7: 733215.26 | C7: =(GETPIVOTDATA("Sales",$A$3,"Year",2017)-GETPIVOTDATA("Sales",$A$3,"Year",2016))/GETPIVOTDATA("Sales",$A$3,"Year",2016) -> 0.20355962
A8: Grand Total | B8: 2297200.9

Sheet Region_Analysis
B3: Row Labels | C3: Total Profit | D3: Total Revenue | E3: Margin %
B4: Central | C4: 200826.91 | D4: 501239.89 | E4: =GETPIVOTDATA("Total Profit",$B$3,"Region","Central")/GETPIVOTDATA("Total Revenue",$B$3,"Region","Central") -> 0.40066028
B5: East | C5: 274346.63 | D5: 678781.24 | E5: =GETPIVOTDATA("Total Profit",$B$3,"Region","East")/GETPIVOTDATA("Total Revenue",$B$3,"Region","East") -> 0.40417533
B6: South | C6: 158262.42 | D6: 391721.91 | E6: =GETPIVOTDATA("Total Profit",$B$3,"Region","South")/GETPIVOTDATA("Total Revenue",$B$3,"Region","South") -> 0.40401729
B7: West | C7: 290152.08 | D7: 725457.82 | E7: =GETPIVOTDATA("Total Profit",$B$3,"Region","West")/GETPIVOTDATA("Total Revenue",$B$3,"Region","West") -> 0.39995721
B8: Grand Total | C8: 923588.06 | D8: 2297200.9
B10: 1) West region contributes the highest revenue but has comparatively lower margins.
B11: 2) East region shows balanced revenue and profitability.
B12: 3) Central region may require cost optimisation.

Sheet Category_Analysis
A3: Row Labels | B3: Total Profit | C3: Total Revenue | D3: Margin %
A4: Furniture | B4: 259699.93 | C4: 741999.8 | D4: =GETPIVOTDATA("Total Profit",$A$3,"Category","Furniture")/GETPIVOTDATA("Total Revenue",$A$3,"Category","Furniture") -> 0.35
A5: Office Supplies | B5: 287618.81 | C5: 719047.03 | D5: =GETPIVOTDATA("Total Profit",$A$3,"Category","Office Supplies")/GETPIVOTDATA("Total Revenue",$A$3,"Category","Office Supplies") -> 0.4
A6: Technology | B6: 376269.31 | C6: 836154.03 | D6: =GETPIVOTDATA("Total Profit",$A$3,"Category","Technology")/GETPIVOTDATA("Total Revenue",$A$3,"Category","Technology") -> 0.45
A7: Grand Total | B7: 923588.06 | C7: 2297200.9
A9: 1)Technology category generates strong profit with high margins, making it a key focus area.
A10: 2)Furniture contributes significantly to revenue but has comparatively lower margins, indicating cost pressure.
A11: 3)Office Supplies shows stable but moderate performance.

Sheet Raw_Data
A1: Row ID | B1: Order ID | C1: Order Date | D1: Ship Date | E1: Ship Mode | F1: Customer ID | G1: Customer Name | H1: Segment | I1: Country | J1: City | K1: State | L1: Postal Code | M1: Region | N1: Product ID | O1: Category | P1: Sub-Category | Q1: Product Name | R1: Sales | S1: Quantity | T1: Discount | U1: Profit | V1: Cost_% | W1: Cost | X1: Gross_Profit_Recalc | Y1: Margin_% | Z1: Year
A2: 1 | B2: CA-2016-152156 | C2: 42682 | D2: 42685 | E2: Second Class | F2: CG-12520 | G2: Claire Gute | H2: Consumer | I2: United States | J2: Henderson | K2: Kentucky | L2: 42420 | M2: South | N2: FUR-BO-10001798 | O2: Furniture | P2: Bookcases | Q2: Bush Somerset Collection Bookcase | R2: 261.96 | S2: 2 | T2: 0 | U2: 41.9136 | V2: =_xlfn.XLOOKUP(Sales_Data[[#This Row],[Category]],Assumptions_Model!A:A, Assumptions_Model!B:B) -> 0.65 | W2: =Sales_Data[[#This Row],[Sales]]*Sales_Data[[#This Row],[Cost_%]] -> 170.274 | X2: =Sales_Data[[#This Row],[Sales]]-Sales_Data[[#This Row],[Cost]] -> 91.686 | Y2: =Sales_Data[[#This Row],[Gross_Profit_Recalc]]/Sales_Data[[#This Row],[Sales]] -> 0.35 | Z2: =YEAR(Sales_Data[[#This Row],[Order Date]]) -> 2016
A3: 2 | B3: CA-2016-152156 | C3: 42682 | D3: 42685 | E3: Second Class | F3: CG-12520 | G3: Claire Gute | H3: Consumer | I3: United States | J3: Henderson | K3: Kentucky | L3: 42420 | M3: South | N3: FUR-CH-10000454 | O3: Furniture | P3: Chairs | Q3: Hon Deluxe Fabric Upholstered Stacking Chairs, Rounded Back | R3: 731.94 | S3: 3 | T3: 0 | U3: 219.582 | V3: =_xlfn.XLOOKUP(Sales_Data[[#This Row],[Category]],Assumptions_Model!A:A, Assumptions_Model!B:B) -> 0.65 | W3: =Sales_Data[[#This Row],[Sales]]*Sales_Data[[#This Row],[Cost_%]] -> 475.761 | X3: =Sales_Data[[#This Row],[Sales]]-Sales_Data[[#This Row],[Cost]] -> 256.179 | Y3: =Sales_Data[[#This Row],[Gross_Profit_Recalc]]/Sales_Data[[#This Row],[Sales]] -> 0.35 | Z3: =YEAR(Sales_Data[[#This Row],[Order Date]]) -> 2016
A4: 3 | B4: CA-2016-138688 | C4: 42533 | D4: 42537 | E4: Second Class | F4: DV-13045 | G4: Darrin Van Huff | H4: Corporate | I4: United States | J4: Los Angeles | K4: California | L4: 90036 | M4: West | N4: OFF-LA-10000240 | O4: Office Supplies | P4: Labels | Q4: Self-Adhesive Address Labels for Typewriters by Universal | R4: 14.62 | S4: 2 | T4: 0 | U4: 6.8714 | V4: =_xlfn.XLOOKUP(Sales_Data[[#This Row],[Category]],Assumptions_Model!A:A, Assumptions_Model!B:B) -> 0.6 | W4: =Sales_Data[[#This Row],[Sales]]*Sales_Data[[#This Row],[Cost_%]] -> 8.772 | X4: =Sales_Data[[#This Row],[Sales]]-Sales_Data[[#This Row],[Cost]] -> 5.848 | Y4: =Sales_Data[[#This Row],[Gross_Profit_Recalc]]/Sales_Data[[#This Row],[Sales]] -> 0.4 | Z4: =YEAR(Sales_Data[[#This Row],[Order Date]]) -> 2016
A5: 4 | B5: US-2015-108966 | C5: 42288 | D5: 42295 | E5: Standard Class | F5: SO-20335 | G5: Sean O'Donnell | H5: Consumer | I5: United States | J5: Fort Lauderdale | K5: Florida | L5: 33311 | M5: South | N5: FUR-TA-10000577 | O5: Furniture | P5: Tables | Q5: Bretford CR4500 Series Slim Rectangular Table | R5: 957.5775 | S5: 5 | T5: 0.45 | U5: -383.031 | V5: =_xlfn.XLOOKUP(Sales_Data[[#This Row],[Category]],Assumptions_Model!A:A, Assumptions_Model!B:B) -> 0.65 | W5: =Sales_Data[[#This Row],[Sales]]*Sales_Data[[#This Row],[Cost_%]] -> 622.42538 | X5: =Sales_Data[[#This Row],[Sales]]-Sales_Data[[#This Row],[Cost]] -> 335.15212 | Y5: =Sales_Data[[#This Row],[Gross_Profit_Recalc]]/Sales_Data[[#This Row],[Sales]] -> 0.35 | Z5: =YEAR(Sales_Data[[#This Row],[Order Date]]) -> 2015
A6: 5 | B6: US-2015-108966 | C6: 42288 | D6: 42295 | E6: Standard Class | F6: SO-20335 | G6: Sean O'Donnell | H6: Consumer | I6: United States | J6: Fort Lauderdale | K6: Florida | L6: 33311 | M6: South | N6: OFF-ST-10000760 | O6: Office Supplies | P6: Storage | Q6: Eldon Fold 'N Roll Cart System | R6: 22.368 | S6: 2 | T6: 0.2 | U6: 2.5164 | V6: =_xlfn.XLOOKUP(Sales_Data[[#This Row],[Category]],Assumptions_Model!A:A, Assumptions_Model!B:B) -> 0.6 | W6: =Sales_Data[[#This Row],[Sales]]*Sales_Data[[#This Row],[Cost_%]] -> 13.4208 | X6: =Sales_Data[[#This Row],[Sales]]-Sales_Data[[#This Row],[Cost]] -> 8.9472 | Y6: =Sales_Data[[#This Row],[Gross_Profit_Recalc]]/Sales_Data[[#This Row],[Sales]] -> 0.4 | Z6: =YEAR(Sales_Data[[#This Row],[Order Date]]) -> 2015
A7: 6 | B7: CA-2014-115812 | C7: 41799 | D7: 41804 | E7: Standard Class | F7: BH-11710 | G7: Brosina Hoffman | H7: Consumer | I7: United States | J7: Los Angeles | K7: California | L7: 90032 | M7: West | N7: FUR-FU-10001487 | O7: Furniture | P7: Furnishings | Q7: Eldon Expressions Wood and Plastic Desk Accessories, Cherry Wood | R7: 48.86 | S7: 7 | T7: 0 | U7: 14.1694 | V7: =_xlfn.XLOOKUP(Sales_Data[[#This Row],[Category]],Assumptions_Model!A:A, Assumptions_Model!B:B) -> 0.65 | W7: =Sales_Data[[#This Row],[Sales]]*Sales_Data[[#This Row],[Cost_%]] -> 31.759 | X7: =Sales_Data[[#This Row],[Sales]]-Sales_Data[[#This Row],[Cost]] -> 17.101 | Y7: =Sales_Data[[#This Row],[Gross_Profit_Recalc]]/Sales_Data[[#This Row],[Sales]] -> 0.35 | Z7: =YEAR(Sales_Data[[#This Row],[Order Date]]) -> 2014
A8: 7 | B8: CA-2014-115812 | C8: 41799 | D8: 41804 | E8: Standard Class | F8: BH-11710 | G8: Brosina Hoffman | H8: Consumer | I8: United States | J8: Los Angeles | K8: California | L8: 90032 | M8: West | N8: OFF-AR-10002833 | O8: Office Supplies | P8: Art | Q8: Newell 322 | R8: 7.28 | S8: 4 | T8: 0 | U8: 1.9656 | V8: =_xlfn.XLOOKUP(Sales_Data[[#This Row],[Category]],Assumptions_Model!A:A, Assumptions_Model!B:B) -> 0.6 | W8: =Sales_Data[[#This Row],[Sales]]*Sales_Data[[#This Row],[Cost_%]] -> 4.368 | X8: =Sales_Data[[#This Row],[Sales]]-Sales_Data[[#This Row],[Cost]] -> 2.912 | Y8: =Sales_Data[[#This Row],[Gross_Profit_Recalc]]/Sales_Data[[#This Row],[Sales]] -> 0.4 | Z8: =YEAR(Sales_Data[[#This Row],[Order Date]]) -> 2014
A9: 8 | B9: CA-2014-115812 | C9: 41799 | D9: 41804 | E9: Standard Class | F9: BH-11710 | G9: Brosina Hoffman | H9: Consumer | I9: United States | J9: Los Angeles | K9: California | L9: 90032 | M9: West | N9: TEC-PH-10002275 | O9: Technology | P9: Phones | Q9: Mitel 5320 IP Phone VoIP phone | R9: 907.152 | S9: 6 | T9: 0.2 | U9: 90.7152 | V9: =_xlfn.XLOOKUP(Sales_Data[[#This Row],[Category]],Assumptions_Model!A:A, Assumptions_Model!B:B) -> 0.55 | W9: =Sales_Data[[#This Row],[Sales]]*Sales_Data[[#This Row],[Cost_%]] -> 498.9336 | X9: =Sales_Data[[#This Row],[Sales]]-Sales_Data[[#This Row],[Cost]] -> 408.2184 | Y9: =Sales_Data[[#This Row],[Gross_Profit_Recalc]]/Sales_Data[[#This Row],[Sales]] -> 0.45 | Z9: =YEAR(Sales_Data[[#This Row],[Order Date]]) -> 2014
A10: 9 | B10: CA-2014-115812 | C10: 41799 | D10: 41804 | E10: Standard Class | F10: BH-11710 | G10: Brosina Hoffman | H10: Consumer | I10: United States | J10: Los Angeles | K10: California | L10: 90032 | M10: West | N10: OFF-BI-10003910 | O10: Office Supplies | P10: Binders | Q10: DXL Angle-View Binders with Locking Rings by Samsill | R10: 18.504 | S10: 3 | T10: 0.2 | U10: 5.7825 | V10: =_xlfn.XLOOKUP(Sales_Data[[#This Row],[Category]],Assumptions_Model!A:A, Assumptions_Model!B:B) -> 0.6 | W10: =Sales_Data[[#This Row],[Sales]]*Sales_Data[[#This Row],[Cost_%]] -> 11.1024 | X10: =Sales_Data[[#This Row],[Sales]]-Sales_Data[[#This Row],[Cost]] -> 7.4016 | Y10: =Sales_Data[[#This Row],[Gross_Profit_Recalc]]/Sales_Data[[#This Row],[Sales]] -> 0.4 | Z10: =YEAR(Sales_Data[[#This Row],[Order Date]]) -> 2014
A11: 10 | B11: CA-2014-115812 | C11: 41799 | D11: 41804 | E11: Standard Class | F11: BH-11710 | G11: Brosina Hoffman | H11: Consumer | I11: United States | J11: Los Angeles | K11: California | L11: 90032 | M11: West | N11: OFF-AP-10002892 | O11: Office Supplies | P11: Appliances | Q11: Belkin F5C206VTEL 6 Outlet Surge | R11: 114.9 | S11: 5 | T11: 0 | U11: 34.47 | V11: =_xlfn.XLOOKUP(Sales_Data[[#This Row],[Category]],Assumptions_Model!A:A, Assumptions_Model!B:B) -> 0.6 | W11: =Sales_Data[[#This Row],[Sales]]*Sales_Data[[#This Row],[Cost_%]] -> 68.94 | X11: =Sales_Data[[#This Row],[Sales]]-Sales_Data[[#This Row],[Cost]] -> 45.96 | Y11: =Sales_Data[[#This Row],[Gross_Profit_Recalc]]/Sales_Data[[#This Row],[Sales]] -> 0.4 | Z11: =YEAR(Sales_Data[[#This Row],[Order Date]]) -> 2014
A12: 11 | B12: CA-2014-115812 | C12: 41799 | D12: 41804 | E12: Standard Class | F12: BH-11710 | G12: Brosina Hoffman | H12: Consumer | I12: United States | J12: Los Angeles | K12: California | L12: 90032 | M12: West | N12: FUR-TA-10001539 | O12: Furniture | P12: Tables | Q12: Chromcraft Rectangular Conference Tables | R12: 1706.184 | S12: 9 | T12: 0.2 | U12: 85.3092 | V12: =_xlfn.XLOOKUP(Sales_Data[[#This Row],[Category]],Assumptions_Model!A:A, Assumptions_Model!B:B) -> 0.65 | W12: =Sales_Data[[#This Row],[Sales]]*Sales_Data[[#This Row],[Cost_%]] -> 1109.0196 | X12: =Sales_Data[[#This Row],[Sales]]-Sales_Data[[#This Row],[Cost]] -> 597.1644 | Y12: =Sales_Data[[#This Row],[Gross_Profit_Recalc]]/Sales_Data[[#This Row],[Sales]] -> 0.35 | Z12: =YEAR(Sales_Data[[#This Row],[Order Date]]) -> 2014
A13: 12 | B13: CA-2014-115812 | C13: 41799 | D13: 41804 | E13: Standard Class | F13: BH-11710 | G13: Brosina Hoffman | H13: Consumer | I13: United States | J13: Los Angeles | K13: California | L13: 90032 | M13: West | N13: TEC-PH-10002033 | O13: Technology | P13: Phones | Q13: Konftel 250 Conference†phone†- Charcoal black | R13: 911.424 | S13: 4 | T13: 0.2 | U13: 68.3568 | V13: =_xlfn.XLOOKUP(Sales_Data[[#This Row],[Category]],Assumptions_Model!A:A, Assumptions_Model!B:B) -> 0.55 | W13: =Sales_Data[[#This Row],[Sales]]*Sales_Data[[#This Row],[Cost_%]] -> 501.2832 | X13: =Sales_Data[[#This Row],[Sales]]-Sales_Data[[#This Row],[Cost]] -> 410.1408 | Y13: =Sales_Data[[#This Row],[Gross_Profit_Recalc]]/Sales_Data[[#This Row],[Sales]] -> 0.45 | Z13: =YEAR(Sales_Data[[#This Row],[Order Date]]) -> 2014
... A9995: 9994 | B9995: CA-2017-119914 | C9995: 42859 | D9995: 42864 | E9995: Second Class | F9995: CC-12220 | G9995: Chris Cortes | H9995: Consumer | I9995: United States | J9995: Westminster | K9995: California | L9995: 92683 | M9995: West | N9995: OFF-AP-10002684 | O9995: Office Supplies | P9995: Appliances | Q9995: Acco 7-Outlet Masterpiece Power Center, Wihtout Fax/Phone Line Protection | R9995: 243.16 | S9995: 2 | T9995: 0 | U9995: 72.948 | V9995: =_xlfn.XLOOKUP(Sales_Data[[#This Row],[Category]],Assumptions_Model!A:A, Assumptions_Model!B:B) -> 0.6 | W9995: =Sales_Data[[#This Row],[Sales]]*Sales_Data[[#This Row],[Cost_%]] -> 145.896 | X9995: =Sales_Data[[#This Row],[Sales]]-Sales_Data[[#This Row],[Cost]] -> 97.264 | Y9995: =Sales_Data[[#This Row],[Gross_Profit_Recalc]]/Sales_Data[[#This Row],[Sales]] -> 0.4 | Z9995: =YEAR(Sales_Data[[#This Row],[Order Date]]) -> 2017
